epath/__init__.py
epath/epath.py
epath-0.7.dist-info/LICENCE.txt
epath-0.7.dist-info/METADATA
epath-0.7.dist-info/WHEEL
epath-0.7.dist-info/top_level.txt
epath-0.7.dist-info/RECORD
